nonebot_plugin_group_info/__init__.py
nonebot_plugin_group_info-0.1.0.dist-info/METADATA
nonebot_plugin_group_info-0.1.0.dist-info/WHEEL
nonebot_plugin_group_info-0.1.0.dist-info/RECORD
